{
 "accept_payment": 0,
 "allow_comments": 0,
 "allow_delete": 0,
 "allow_edit": 0,
 "allow_incomplete": 0,
 "allow_multiple": 0,
 "allow_print": 0,
 "amount": 0.0,
 "amount_based_on_field": 0,
 "anonymous": 0,
 "apply_document_permissions": 0,
 "button_label": "Save",
 "condition_json": "[]",
 "creation": "2025-02-26 17:58:12.063999",
 "currency": "PKR",
 "doc_type": "Student Applicant",
 "docstatus": 0,
 "doctype": "Web Form",
 "idx": 0,
 "is_standard": 1,
 "list_columns": [],
 "login_required": 0,
 "max_attachment_size": 0,
 "modified": "2025-02-28 15:09:29.215763",
 "modified_by": "Administrator",
 "module": "Akf Education",
 "name": "orphan-applicant",
 "owner": "Administrator",
 "payment_button_label": "Buy Now",
 "published": 1,
 "route": "orphan-applicant",
 "show_attachments": 0,
 "show_list": 0,
 "show_sidebar": 0,
 "title": "Orphan Applicant",
 "web_form_fields": [
  {
   "allow_read_on_all_link_options": 0,
   "fieldname": "first_name",
   "fieldtype": "Data",
   "hidden": 0,
   "label": "First Name",
   "max_length": 0,
   "max_value": 0,
   "precision": "",
   "read_only": 0,
   "reqd": 1,
   "show_in_filter": 0
  },
  {
   "allow_read_on_all_link_options": 0,
   "fieldname": "last_name",
   "fieldtype": "Data",
   "hidden": 0,
   "label": "Last Name",
   "max_length": 0,
   "max_value": 0,
   "precision": "",
   "read_only": 0,
   "reqd": 0,
   "show_in_filter": 0
  },
  {
   "allow_read_on_all_link_options": 0,
   "fieldname": "place_of_birth",
   "fieldtype": "Data",
   "hidden": 0,
   "label": "Place Of Birth",
   "max_length": 0,
   "max_value": 0,
   "precision": "",
   "read_only": 0,
   "reqd": 0,
   "show_in_filter": 0
  },
  {
   "allow_read_on_all_link_options": 0,
   "fieldname": "mother_language",
   "fieldtype": "Data",
   "hidden": 0,
   "label": "Mother Language",
   "max_length": 0,
   "max_value": 0,
   "precision": "",
   "read_only": 0,
   "reqd": 0,
   "show_in_filter": 0
  },
  {
   "allow_read_on_all_link_options": 0,
   "fieldname": "permanent_address",
   "fieldtype": "Data",
   "hidden": 0,
   "label": "Permanent Address",
   "max_length": 0,
   "max_value": 0,
   "precision": "",
   "read_only": 0,
   "reqd": 0,
   "show_in_filter": 0
  },
  {
   "allow_read_on_all_link_options": 0,
   "fieldname": "student_category",
   "fieldtype": "Link",
   "hidden": 1,
   "label": "Student Category",
   "max_length": 0,
   "max_value": 0,
   "options": "Student Category",
   "precision": "",
   "read_only": 0,
   "reqd": 0,
   "show_in_filter": 0
  },
  {
   "allow_read_on_all_link_options": 0,
   "fieldname": "academic_term",
   "fieldtype": "Link",
   "hidden": 0,
   "label": "Academic Term",
   "max_length": 0,
   "max_value": 0,
   "options": "Academic Term",
   "precision": "",
   "read_only": 0,
   "reqd": 0,
   "show_in_filter": 0
  },
  {
   "allow_read_on_all_link_options": 0,
   "fieldname": "number_of_siblings",
   "fieldtype": "Data",
   "hidden": 0,
   "label": "Number Of Siblings",
   "max_length": 0,
   "max_value": 0,
   "precision": "",
   "read_only": 0,
   "reqd": 0,
   "show_in_filter": 0
  },
  {
   "allow_read_on_all_link_options": 0,
   "fieldname": "sisters",
   "fieldtype": "Int",
   "hidden": 0,
   "label": "Number Of Sisters",
   "max_length": 0,
   "max_value": 0,
   "precision": "",
   "read_only": 0,
   "reqd": 0,
   "show_in_filter": 0
  },
  {
   "allow_read_on_all_link_options": 0,
   "fieldname": "column_break_8",
   "fieldtype": "Column Break",
   "hidden": 0,
   "max_length": 0,
   "max_value": 0,
   "precision": "",
   "read_only": 0,
   "reqd": 0,
   "show_in_filter": 0
  },
  {
   "allow_read_on_all_link_options": 0,
   "fieldname": "middle_name",
   "fieldtype": "Data",
   "hidden": 0,
   "label": "Middle Name",
   "max_length": 0,
   "max_value": 0,
   "precision": "",
   "read_only": 0,
   "reqd": 0,
   "show_in_filter": 0
  },
  {
   "allow_read_on_all_link_options": 0,
   "fieldname": "date_of_birth1",
   "fieldtype": "Date",
   "hidden": 0,
   "label": "Date Of Birth",
   "max_length": 0,
   "max_value": 0,
   "precision": "",
   "read_only": 0,
   "reqd": 0,
   "show_in_filter": 0
  },
  {
   "allow_read_on_all_link_options": 0,
   "fieldname": "program",
   "fieldtype": "Link",
   "hidden": 0,
   "label": "Class",
   "max_length": 0,
   "max_value": 0,
   "options": "Program",
   "precision": "",
   "read_only": 0,
   "reqd": 1,
   "show_in_filter": 0
  },
  {
   "allow_read_on_all_link_options": 0,
   "fieldname": "gender1",
   "fieldtype": "Select",
   "hidden": 0,
   "label": "Gender",
   "max_length": 0,
   "max_value": 0,
   "options": "\nMale\nFemale\nOthers",
   "precision": "",
   "read_only": 0,
   "reqd": 0,
   "show_in_filter": 0
  },
  {
   "allow_read_on_all_link_options": 0,
   "fieldname": "blood_group",
   "fieldtype": "Select",
   "hidden": 0,
   "label": "Blood Group",
   "max_length": 0,
   "max_value": 0,
   "options": "\nA+\nA-\nB+\nB-\nO+\nO-\nAB+\nAB-",
   "precision": "",
   "read_only": 0,
   "reqd": 0,
   "show_in_filter": 0
  },
  {
   "allow_read_on_all_link_options": 0,
   "fieldname": "academic_year",
   "fieldtype": "Link",
   "hidden": 0,
   "label": "Academic Year",
   "max_length": 0,
   "max_value": 0,
   "options": "Academic Year",
   "precision": "",
   "read_only": 0,
   "reqd": 1,
   "show_in_filter": 0
  },
  {
   "allow_read_on_all_link_options": 0,
   "fieldname": "naming_series",
   "fieldtype": "Select",
   "hidden": 1,
   "label": "Naming Series",
   "max_length": 0,
   "max_value": 0,
   "options": "EDU-APP-.YYYY.-",
   "precision": "",
   "read_only": 0,
   "reqd": 0,
   "show_in_filter": 0
  },
  {
   "allow_read_on_all_link_options": 0,
   "fieldname": "application_status",
   "fieldtype": "Select",
   "hidden": 1,
   "label": "Application Status",
   "max_length": 0,
   "max_value": 0,
   "options": "Applied\nApproved\nRejected\nAdmitted",
   "precision": "",
   "read_only": 1,
   "reqd": 0,
   "show_in_filter": 0
  },
  {
   "allow_read_on_all_link_options": 0,
   "fieldname": "brothers",
   "fieldtype": "Int",
   "hidden": 0,
   "label": "Number Of Brothers",
   "max_length": 0,
   "max_value": 0,
   "precision": "",
   "read_only": 0,
   "reqd": 0,
   "show_in_filter": 0
  },
  {
   "allow_read_on_all_link_options": 0,
   "fieldname": "student_admission",
   "fieldtype": "Link",
   "hidden": 1,
   "label": "Student Admission",
   "max_length": 0,
   "max_value": 0,
   "options": "Student Admission",
   "precision": "",
   "read_only": 0,
   "reqd": 0,
   "show_in_filter": 0
  },
  {
   "allow_read_on_all_link_options": 0,
   "default": "0",
   "fieldname": "paid",
   "fieldtype": "Check",
   "hidden": 1,
   "label": "Paid",
   "max_length": 0,
   "max_value": 0,
   "precision": "",
   "read_only": 0,
   "reqd": 0,
   "show_in_filter": 0
  },
  {
   "allow_read_on_all_link_options": 0,
   "fieldname": "",
   "fieldtype": "Page Break",
   "hidden": 0,
   "label": "",
   "max_length": 0,
   "max_value": 0,
   "options": "",
   "precision": "",
   "read_only": 0,
   "reqd": 0,
   "show_in_filter": 0
  },
  {
   "allow_read_on_all_link_options": 0,
   "fieldname": "father_details",
   "fieldtype": "Section Break",
   "hidden": 0,
   "label": "Father's Details",
   "max_length": 0,
   "max_value": 0,
   "precision": "",
   "read_only": 0,
   "reqd": 0,
   "show_in_filter": 0
  },
  {
   "allow_read_on_all_link_options": 0,
   "fieldname": "name1",
   "fieldtype": "Data",
   "hidden": 0,
   "label": "Name",
   "max_length": 0,
   "max_value": 0,
   "precision": "",
   "read_only": 0,
   "reqd": 0,
   "show_in_filter": 0
  },
  {
   "allow_read_on_all_link_options": 0,
   "fieldname": "father_occupation",
   "fieldtype": "Data",
   "hidden": 0,
   "label": "Father Occupation",
   "max_length": 0,
   "max_value": 0,
   "precision": "",
   "read_only": 0,
   "reqd": 0,
   "show_in_filter": 0
  },
  {
   "allow_read_on_all_link_options": 0,
   "fieldname": "father_reason_death",
   "fieldtype": "Data",
   "hidden": 0,
   "label": "Reason Of Death",
   "max_length": 0,
   "max_value": 0,
   "precision": "",
   "read_only": 0,
   "reqd": 0,
   "show_in_filter": 0
  },
  {
   "allow_read_on_all_link_options": 0,
   "fieldname": "attach_death_certificate",
   "fieldtype": "Attach Image",
   "hidden": 0,
   "label": "Attach Death Certificate",
   "max_length": 0,
   "max_value": 0,
   "precision": "",
   "read_only": 0,
   "reqd": 0,
   "show_in_filter": 0
  },
  {
   "allow_read_on_all_link_options": 0,
   "fieldname": "column_break_lnba",
   "fieldtype": "Column Break",
   "hidden": 0,
   "label": "",
   "max_length": 0,
   "max_value": 0,
   "precision": "",
   "read_only": 0,
   "reqd": 0,
   "show_in_filter": 0
  },
  {
   "allow_read_on_all_link_options": 0,
   "fieldname": "cnic1",
   "fieldtype": "Int",
   "hidden": 0,
   "label": "CNIC",
   "max_length": 0,
   "max_value": 0,
   "precision": "",
   "read_only": 0,
   "reqd": 0,
   "show_in_filter": 0
  },
  {
   "allow_read_on_all_link_options": 0,
   "fieldname": "father_dob",
   "fieldtype": "Date",
   "hidden": 0,
   "label": "Date Of Birth",
   "max_length": 0,
   "max_value": 0,
   "precision": "",
   "read_only": 0,
   "reqd": 0,
   "show_in_filter": 0
  },
  {
   "allow_read_on_all_link_options": 0,
   "fieldname": "father_death_place",
   "fieldtype": "Data",
   "hidden": 0,
   "label": "Place Of Death",
   "max_length": 0,
   "max_value": 0,
   "precision": "",
   "read_only": 0,
   "reqd": 0,
   "show_in_filter": 0
  },
  {
   "allow_read_on_all_link_options": 0,
   "fieldname": "",
   "fieldtype": "Page Break",
   "hidden": 0,
   "label": "",
   "max_length": 0,
   "max_value": 0,
   "options": "",
   "precision": "",
   "read_only": 0,
   "reqd": 0,
   "show_in_filter": 0
  },
  {
   "allow_read_on_all_link_options": 0,
   "fieldname": "mother_details",
   "fieldtype": "Section Break",
   "hidden": 0,
   "label": "Mother's Details",
   "max_length": 0,
   "max_value": 0,
   "precision": "",
   "read_only": 0,
   "reqd": 0,
   "show_in_filter": 0
  },
  {
   "allow_read_on_all_link_options": 0,
   "fieldname": "name2",
   "fieldtype": "Data",
   "hidden": 0,
   "label": "Name",
   "max_length": 0,
   "max_value": 0,
   "precision": "",
   "read_only": 0,
   "reqd": 0,
   "show_in_filter": 0
  },
  {
   "allow_read_on_all_link_options": 0,
   "fieldname": "cnic",
   "fieldtype": "Int",
   "hidden": 0,
   "label": "CNIC",
   "max_length": 0,
   "max_value": 0,
   "precision": "",
   "read_only": 0,
   "reqd": 0,
   "show_in_filter": 0
  },
  {
   "allow_read_on_all_link_options": 0,
   "fieldname": "husband_name",
   "fieldtype": "Data",
   "hidden": 0,
   "label": "Husband's Name",
   "max_length": 0,
   "max_value": 0,
   "precision": "",
   "read_only": 0,
   "reqd": 0,
   "show_in_filter": 0
  },
  {
   "allow_read_on_all_link_options": 0,
   "fieldname": "mother_dob",
   "fieldtype": "Date",
   "hidden": 0,
   "label": "Date Of Birth",
   "max_length": 0,
   "max_value": 0,
   "precision": "",
   "read_only": 0,
   "reqd": 0,
   "show_in_filter": 0
  },
  {
   "allow_read_on_all_link_options": 0,
   "fieldname": "column_break_snkq",
   "fieldtype": "Column Break",
   "hidden": 0,
   "label": "",
   "max_length": 0,
   "max_value": 0,
   "precision": "",
   "read_only": 0,
   "reqd": 0,
   "show_in_filter": 0
  },
  {
   "allow_read_on_all_link_options": 0,
   "fieldname": "alive_status",
   "fieldtype": "Select",
   "hidden": 0,
   "label": "Alive Status",
   "max_length": 0,
   "max_value": 0,
   "options": "\nAlive\nDeath",
   "precision": "",
   "read_only": 0,
   "reqd": 0,
   "show_in_filter": 0
  },
  {
   "allow_read_on_all_link_options": 0,
   "depends_on": "eval:doc.alive_status==\"Death\"\n",
   "fieldname": "reason_of_death",
   "fieldtype": "Data",
   "hidden": 0,
   "label": "Reason Of Death",
   "max_length": 0,
   "max_value": 0,
   "precision": "",
   "read_only": 0,
   "reqd": 0,
   "show_in_filter": 0
  },
  {
   "allow_read_on_all_link_options": 0,
   "depends_on": "eval:doc.alive_status==\"Death\"\n",
   "fieldname": "place_of_death",
   "fieldtype": "Data",
   "hidden": 0,
   "label": "Place Of Death",
   "max_length": 0,
   "max_value": 0,
   "precision": "",
   "read_only": 0,
   "reqd": 0,
   "show_in_filter": 0
  },
  {
   "allow_read_on_all_link_options": 0,
   "fieldname": "section_break_23",
   "fieldtype": "Section Break",
   "hidden": 0,
   "max_length": 0,
   "max_value": 0,
   "precision": "",
   "read_only": 0,
   "reqd": 0,
   "show_in_filter": 0
  },
  {
   "allow_read_on_all_link_options": 0,
   "fieldname": "amended_from",
   "fieldtype": "Link",
   "hidden": 1,
   "label": "Amended From",
   "max_length": 0,
   "max_value": 0,
   "options": "Student Applicant",
   "precision": "",
   "read_only": 1,
   "reqd": 0,
   "show_in_filter": 0
  },
  {
   "allow_read_on_all_link_options": 0,
   "fieldname": "section_break_4",
   "fieldtype": "Section Break",
   "hidden": 0,
   "max_length": 0,
   "max_value": 0,
   "precision": "",
   "read_only": 0,
   "reqd": 0,
   "show_in_filter": 0
  },
  {
   "allow_read_on_all_link_options": 0,
   "fieldname": "gender",
   "fieldtype": "Link",
   "hidden": 1,
   "label": "Gender",
   "max_length": 0,
   "max_value": 0,
   "options": "Gender",
   "precision": "",
   "read_only": 0,
   "reqd": 0,
   "show_in_filter": 0
  },
  {
   "allow_read_on_all_link_options": 0,
   "fieldname": "column_break_12",
   "fieldtype": "Column Break",
   "hidden": 0,
   "max_length": 0,
   "max_value": 0,
   "precision": "",
   "read_only": 0,
   "reqd": 0,
   "show_in_filter": 0
  },
  {
   "allow_read_on_all_link_options": 0,
   "fieldname": "student_mobile_number",
   "fieldtype": "Data",
   "hidden": 1,
   "label": "Student Mobile Number",
   "max_length": 0,
   "max_value": 0,
   "precision": "",
   "read_only": 0,
   "reqd": 0,
   "show_in_filter": 0
  },
  {
   "allow_read_on_all_link_options": 0,
   "fieldname": "nationality",
   "fieldtype": "Data",
   "hidden": 1,
   "label": "Nationality",
   "max_length": 0,
   "max_value": 0,
   "precision": "",
   "read_only": 0,
   "reqd": 0,
   "show_in_filter": 0
  },
  {
   "allow_read_on_all_link_options": 0,
   "fieldname": "relations_tab",
   "fieldtype": "Page Break",
   "hidden": 0,
   "label": "Guardian Info",
   "max_length": 0,
   "max_value": 0,
   "precision": "",
   "read_only": 0,
   "reqd": 0,
   "show_in_filter": 0
  },
  {
   "allow_read_on_all_link_options": 0,
   "fieldname": "section_break_20",
   "fieldtype": "Section Break",
   "hidden": 0,
   "label": "Guardian Details",
   "max_length": 0,
   "max_value": 0,
   "precision": "",
   "read_only": 0,
   "reqd": 0,
   "show_in_filter": 0
  },
  {
   "allow_read_on_all_link_options": 0,
   "fieldname": "guardians",
   "fieldtype": "Table",
   "hidden": 1,
   "label": "Guardians",
   "max_length": 0,
   "max_value": 0,
   "options": "Student Guardian",
   "precision": "",
   "read_only": 0,
   "reqd": 0,
   "show_in_filter": 0
  },
  {
   "allow_read_on_all_link_options": 0,
   "fieldname": "name5",
   "fieldtype": "Data",
   "hidden": 0,
   "label": "Name",
   "max_length": 0,
   "max_value": 0,
   "precision": "",
   "read_only": 0,
   "reqd": 0,
   "show_in_filter": 0
  },
  {
   "allow_read_on_all_link_options": 0,
   "fieldname": "cnic12",
   "fieldtype": "Int",
   "hidden": 0,
   "label": "CNIC",
   "max_length": 0,
   "max_value": 0,
   "precision": "",
   "read_only": 0,
   "reqd": 0,
   "show_in_filter": 0
  },
  {
   "allow_read_on_all_link_options": 0,
   "fieldname": "contact_number",
   "fieldtype": "Data",
   "hidden": 0,
   "label": "Contact Number",
   "max_length": 0,
   "max_value": 0,
   "precision": "",
   "read_only": 0,
   "reqd": 0,
   "show_in_filter": 0
  },
  {
   "allow_read_on_all_link_options": 0,
   "fieldname": "relation_with_child",
   "fieldtype": "Data",
   "hidden": 0,
   "label": "Relation With Child",
   "max_length": 0,
   "max_value": 0,
   "precision": "",
   "read_only": 0,
   "reqd": 0,
   "show_in_filter": 0
  },
  {
   "allow_read_on_all_link_options": 0,
   "fieldname": "education",
   "fieldtype": "Data",
   "hidden": 0,
   "label": "Education",
   "max_length": 0,
   "max_value": 0,
   "precision": "",
   "read_only": 0,
   "reqd": 0,
   "show_in_filter": 0
  },
  {
   "allow_read_on_all_link_options": 0,
   "fieldname": "column_break_itas",
   "fieldtype": "Column Break",
   "hidden": 0,
   "label": "",
   "max_length": 0,
   "max_value": 0,
   "precision": "",
   "read_only": 0,
   "reqd": 0,
   "show_in_filter": 0
  },
  {
   "allow_read_on_all_link_options": 0,
   "fieldname": "gender2",
   "fieldtype": "Select",
   "hidden": 0,
   "label": "Gender",
   "max_length": 0,
   "max_value": 0,
   "options": "\nMale\nFemale",
   "precision": "",
   "read_only": 0,
   "reqd": 0,
   "show_in_filter": 0
  },
  {
   "allow_read_on_all_link_options": 0,
   "fieldname": "address",
   "fieldtype": "Data",
   "hidden": 0,
   "label": "Address",
   "max_length": 0,
   "max_value": 0,
   "precision": "",
   "read_only": 0,
   "reqd": 0,
   "show_in_filter": 0
  },
  {
   "allow_read_on_all_link_options": 0,
   "fieldname": "occupation_details",
   "fieldtype": "Data",
   "hidden": 0,
   "label": "Occupation Details",
   "max_length": 0,
   "max_value": 0,
   "precision": "",
   "read_only": 0,
   "reqd": 0,
   "show_in_filter": 0
  },
  {
   "allow_read_on_all_link_options": 0,
   "fieldname": "marital_status",
   "fieldtype": "Select",
   "hidden": 0,
   "label": "Marital Status",
   "max_length": 0,
   "max_value": 0,
   "options": "\nMarried\nEngaged\nSingle",
   "precision": "",
   "read_only": 0,
   "reqd": 0,
   "show_in_filter": 0
  },
  {
   "allow_read_on_all_link_options": 0,
   "fieldname": "siblings",
   "fieldtype": "Table",
   "hidden": 1,
   "label": "Siblings",
   "max_length": 0,
   "max_value": 0,
   "options": "Student Sibling",
   "precision": "",
   "read_only": 0,
   "reqd": 0,
   "show_in_filter": 0
  },
  {
   "allow_read_on_all_link_options": 0,
   "fieldname": "address_tab",
   "fieldtype": "Page Break",
   "hidden": 0,
   "label": "Address",
   "max_length": 0,
   "max_value": 0,
   "precision": "",
   "read_only": 0,
   "reqd": 0,
   "show_in_filter": 0
  },
  {
   "allow_read_on_all_link_options": 0,
   "fieldname": "home_address",
   "fieldtype": "Section Break",
   "hidden": 0,
   "label": "Details",
   "max_length": 0,
   "max_value": 0,
   "precision": "",
   "read_only": 0,
   "reqd": 0,
   "show_in_filter": 0
  },
  {
   "allow_read_on_all_link_options": 0,
   "fieldname": "address_line_1",
   "fieldtype": "Data",
   "hidden": 0,
   "label": "Address Line 1",
   "max_length": 0,
   "max_value": 0,
   "precision": "",
   "read_only": 0,
   "reqd": 0,
   "show_in_filter": 0
  },
  {
   "allow_read_on_all_link_options": 0,
   "fieldname": "address_line_2",
   "fieldtype": "Data",
   "hidden": 0,
   "label": "Address Line 2",
   "max_length": 0,
   "max_value": 0,
   "precision": "",
   "read_only": 0,
   "reqd": 0,
   "show_in_filter": 0
  },
  {
   "allow_read_on_all_link_options": 0,
   "fieldtype": "Data",
   "hidden": 0,
   "label": "Region",
   "max_length": 0,
   "max_value": 0,
   "precision": "",
   "read_only": 0,
   "reqd": 0,
   "show_in_filter": 0
  },
  {
   "allow_read_on_all_link_options": 0,
   "fieldtype": "Data",
   "hidden": 0,
   "label": "Country",
   "max_length": 0,
   "max_value": 0,
   "precision": "",
   "read_only": 0,
   "reqd": 0,
   "show_in_filter": 0
  },
  {
   "allow_read_on_all_link_options": 0,
   "fieldname": "city",
   "fieldtype": "Data",
   "hidden": 1,
   "label": "City",
   "max_length": 0,
   "max_value": 0,
   "precision": "",
   "read_only": 0,
   "reqd": 0,
   "show_in_filter": 0
  },
  {
   "allow_read_on_all_link_options": 0,
   "fieldname": "column_break_23",
   "fieldtype": "Column Break",
   "hidden": 0,
   "max_length": 0,
   "max_value": 0,
   "precision": "",
   "read_only": 0,
   "reqd": 0,
   "show_in_filter": 0
  },
  {
   "allow_read_on_all_link_options": 0,
   "fieldname": "state",
   "fieldtype": "Data",
   "hidden": 1,
   "label": "State",
   "max_length": 0,
   "max_value": 0,
   "precision": "",
   "read_only": 0,
   "reqd": 0,
   "show_in_filter": 0
  },
  {
   "allow_read_on_all_link_options": 0,
   "fieldname": "pincode",
   "fieldtype": "Data",
   "hidden": 1,
   "label": "Pincode",
   "max_length": 0,
   "max_value": 0,
   "precision": "",
   "read_only": 0,
   "reqd": 0,
   "show_in_filter": 0
  },
  {
   "allow_read_on_all_link_options": 0,
   "fieldtype": "Attach",
   "hidden": 1,
   "max_length": 0,
   "max_value": 0,
   "precision": "",
   "read_only": 0,
   "reqd": 0,
   "show_in_filter": 0
  },
  {
   "allow_read_on_all_link_options": 0,
   "fieldtype": "Data",
   "hidden": 0,
   "label": "District",
   "max_length": 0,
   "max_value": 0,
   "precision": "",
   "read_only": 0,
   "reqd": 0,
   "show_in_filter": 0
  },
  {
   "allow_read_on_all_link_options": 0,
   "fieldtype": "Data",
   "hidden": 0,
   "label": "Tehsil",
   "max_length": 0,
   "max_value": 0,
   "precision": "",
   "read_only": 0,
   "reqd": 0,
   "show_in_filter": 0
  },
  {
   "allow_read_on_all_link_options": 0,
   "fieldtype": "Data",
   "hidden": 0,
   "label": "UC",
   "max_length": 0,
   "max_value": 0,
   "precision": "",
   "read_only": 0,
   "reqd": 0,
   "show_in_filter": 0
  },
  {
   "allow_read_on_all_link_options": 0,
   "fieldname": "section_break_mzbn",
   "fieldtype": "Section Break",
   "hidden": 0,
   "label": "",
   "max_length": 0,
   "max_value": 0,
   "precision": "",
   "read_only": 0,
   "reqd": 0,
   "show_in_filter": 0
  },
  {
   "allow_read_on_all_link_options": 0,
   "fieldname": "school_type",
   "fieldtype": "Select",
   "hidden": 1,
   "label": "School Type",
   "max_length": 0,
   "max_value": 0,
   "options": "\nInternal\nExternal",
   "precision": "",
   "read_only": 0,
   "reqd": 0,
   "show_in_filter": 0
  },
  {
   "allow_read_on_all_link_options": 0,
   "fieldname": "column_break_fjsd",
   "fieldtype": "Column Break",
   "hidden": 0,
   "label": "",
   "max_length": 0,
   "max_value": 0,
   "precision": "",
   "read_only": 0,
   "reqd": 0,
   "show_in_filter": 0
  },
  {
   "allow_read_on_all_link_options": 0,
   "depends_on": "eval:doc.school_type==\"External\"\n",
   "fieldname": "external",
   "fieldtype": "Link",
   "hidden": 0,
   "label": "External",
   "max_length": 0,
   "max_value": 0,
   "options": "External School",
   "precision": "",
   "read_only": 0,
   "reqd": 0,
   "show_in_filter": 0
  },
  {
   "allow_read_on_all_link_options": 0,
   "fieldname": "section_break_lwec",
   "fieldtype": "Section Break",
   "hidden": 0,
   "label": "",
   "max_length": 0,
   "max_value": 0,
   "precision": "",
   "read_only": 0,
   "reqd": 0,
   "show_in_filter": 0
  },
  {
   "allow_read_on_all_link_options": 0,
   "depends_on": "eval:doc.school_type==\"Internal\"\n",
   "fieldname": "aghosh_home",
   "fieldtype": "Link",
   "hidden": 0,
   "label": "Aghosh Home",
   "max_length": 0,
   "max_value": 0,
   "options": "Aghosh Homes",
   "precision": "",
   "read_only": 0,
   "reqd": 0,
   "show_in_filter": 0
  },
  {
   "allow_read_on_all_link_options": 0,
   "depends_on": "eval:doc.school_type==\"Internal\"\n",
   "fieldname": "room",
   "fieldtype": "Link",
   "hidden": 0,
   "label": "Room",
   "max_length": 0,
   "max_value": 0,
   "options": "Rooms",
   "precision": "",
   "read_only": 0,
   "reqd": 0,
   "show_in_filter": 0
  },
  {
   "allow_read_on_all_link_options": 0,
   "fieldname": "column_break_kyok",
   "fieldtype": "Column Break",
   "hidden": 0,
   "label": "",
   "max_length": 0,
   "max_value": 0,
   "precision": "",
   "read_only": 0,
   "reqd": 0,
   "show_in_filter": 0
  },
  {
   "allow_read_on_all_link_options": 0,
   "depends_on": "eval:doc.school_type==\"Internal\"\n",
   "fieldname": "building",
   "fieldtype": "Link",
   "hidden": 0,
   "label": "Building",
   "max_length": 0,
   "max_value": 0,
   "options": "Building",
   "precision": "",
   "read_only": 0,
   "reqd": 0,
   "show_in_filter": 0
  },
  {
   "allow_read_on_all_link_options": 0,
   "depends_on": "eval:doc.school_type==\"Internal\"\n",
   "fieldname": "bed",
   "fieldtype": "Link",
   "hidden": 0,
   "label": "Bed",
   "max_length": 0,
   "max_value": 0,
   "options": "Beds",
   "precision": "",
   "read_only": 0,
   "reqd": 0,
   "show_in_filter": 0
  },
  {
   "allow_read_on_all_link_options": 0,
   "fieldname": "column_break_lvby",
   "fieldtype": "Column Break",
   "hidden": 0,
   "max_length": 0,
   "max_value": 0,
   "precision": "",
   "read_only": 0,
   "reqd": 0,
   "show_in_filter": 0
  },
  {
   "allow_read_on_all_link_options": 0,
   "fieldname": "section_break_xuzu",
   "fieldtype": "Section Break",
   "hidden": 0,
   "max_length": 0,
   "max_value": 0,
   "precision": "",
   "read_only": 0,
   "reqd": 0,
   "show_in_filter": 0
  }
 ]
}